table_five-0.0.2.dist-info/METADATA
table_five-0.0.2.dist-info/WHEEL
table_five/__init__.py
table_five/table_five.abi3.so
table_five-0.0.2.dist-info/RECORD
